nonebug_saa/__init__.py
nonebug_saa/fixtures.py
nonebug_saa-0.5.0.dist-info/METADATA
nonebug_saa-0.5.0.dist-info/WHEEL
nonebug_saa-0.5.0.dist-info/entry_points.txt
nonebug_saa-0.5.0.dist-info/RECORD
