Metadata-Version: 2.1
Name: nonebug-saa
Version: 0.5.0
Summary: A nonebug helper for nonebot-plugin-send-anything-anything
Home-page: https://github.com/MountainDash/nonebug-saa
License: MIT
Author: felinae98
Author-email: me@felinae98.cn
Requires-Python: >=3.9,<4.0
Classifier: Framework :: Pytest
Classifier: License :: OSI Approved :: MIT License
Classifier: Programming Language :: Python :: 3
Classifier: Programming Language :: Python :: 3.9
Classifier: Programming Language :: Python :: 3.10
Classifier: Programming Language :: Python :: 3.11
Classifier: Programming Language :: Python :: 3.12
Classifier: Programming Language :: Python :: 3.13
Requires-Dist: nonebot-plugin-send-anything-anywhere (>=0.5.0)
Requires-Dist: nonebug (>=0.3.1)
Requires-Dist: pytest-mock (>=3.10.0,<4.0.0)
Project-URL: Documentation, https://github.com/MountainDash/nonebug-saa#readme
Project-URL: Repository, https://github.com/MountainDash/nonebug-saa
